pyembeddedfhir/__init__.py
pyembeddedfhir/commons.py
pyembeddedfhir/errors.py
pyembeddedfhir/fhir_runner.py
pyembeddedfhir/implementations.py
pyembeddedfhir/models.py
pyembeddedfhir-1.1.3.dist-info/AUTHORS.rst
pyembeddedfhir-1.1.3.dist-info/LICENSE
pyembeddedfhir-1.1.3.dist-info/METADATA
pyembeddedfhir-1.1.3.dist-info/WHEEL
pyembeddedfhir-1.1.3.dist-info/top_level.txt
pyembeddedfhir-1.1.3.dist-info/RECORD
