Metadata-Version: 2.1
Name: pyembeddedfhir
Version: 1.1.3
Summary: A simple way to use a 🔥 FHIR server in 🐍 Python integration tests.
Home-page: https://github.com/kdunee/pyembeddedfhir
Author: Kosma Dunikowski
Author-email: kosmadunikowski@gmail.com
License: MIT license
Keywords: pyembeddedfhir
Platform: UNKNOWN
Classifier: Development Status :: 2 - Pre-Alpha
Classifier: Intended Audience :: Developers
Classifier: License :: OSI Approved :: MIT License
Classifier: Natural Language :: English
Classifier: Programming Language :: Python :: 3
Classifier: Programming Language :: Python :: 3.6
Classifier: Programming Language :: Python :: 3.7
Classifier: Programming Language :: Python :: 3.8
Requires-Python: >=3.6
License-File: LICENSE
License-File: AUTHORS.rst
Requires-Dist: docker (>=5.0.3)
Requires-Dist: psutil (>=5.8.0)
Requires-Dist: dataclasses (>=0.6) ; python_version < "3.7"
